test/__init__.py
test/system_test.py
thegmu_imagemanage/__init__.py
thegmu_imagemanage/script.py
thegmu_imagemanage/thegmu_im.py
thegmu_imagemanage/thegmu_im_catalog.py
thegmu_imagemanage/thegmu_im_catalog_excel.py
thegmu_imagemanage/thegmu_im_convert.py
thegmu_imagemanage/thegmu_im_errors.py
thegmu_imagemanage/thegmu_im_excel_file.py
thegmu_imagemanage/thegmu_im_os.py
thegmu_imagemanage/thegmu_im_util.py
thegmu_imagemanage/thegmu_log.py
thegmu_imagemanage-1.0.0.data/scripts/thegmu_im.py
thegmu_imagemanage-1.0.0.dist-info/LICENSE.txt
thegmu_imagemanage-1.0.0.dist-info/METADATA
thegmu_imagemanage-1.0.0.dist-info/WHEEL
thegmu_imagemanage-1.0.0.dist-info/top_level.txt
thegmu_imagemanage-1.0.0.dist-info/RECORD
