Metadata-Version: 2.1
Name: thegmu-imagemanage
Version: 1.0.0
Summary: The GMU Image Manage
Home-page: UNKNOWN
Author: Mybrid Wonderful, The GMU
License: MIT
Keywords: thegmu-imagemanage
Platform: UNKNOWN
Classifier: Environment :: Console
Classifier: Development Status :: 5 - Production/Stable
Classifier: Intended Audience :: Developers
Classifier: Intended Audience :: System Administrators
Classifier: Topic :: Software Development
Classifier: License :: OSI Approved :: MIT License
Classifier: Programming Language :: Python
Classifier: Programming Language :: Python :: 3.6
Requires-Dist: PyYAML
Requires-Dist: filetype
Requires-Dist: Wand
Requires-Dist: openpyxl
Requires-Dist: Pillow
